Metadata-Version: 1.0
Name: mc-cli
Version: 0.0.4
Summary: Machine Colony command line tools
Home-page: https://github.com/machinecolony/mc-cli
Author: Machine Colony
Author-email: francis@machinecolony.com
License: MIT
Platform: UNKNOWN
